djpyscript/__init__.py
djpyscript/extraction.py
djpyscript/fieldfiles.py
djpyscript/fields.py
djpyscript/loaders.py
django_pyscript-0.9.5.dist-info/WHEEL
django_pyscript-0.9.5.dist-info/METADATA
django_pyscript-0.9.5.dist-info/RECORD
